Workbook

Sheet Dashboard
A1: Microsoft Financial Performance Dashboard
A2: 3-Year Analysis | FY2023–FY2025
A4: Revenue | D4: Net Income | G4: Operating Margin
A5: ='Trend Analysis'!D5 -> 281724 | D5: ='Trend Analysis'!D6 -> 101832 | G5: ='Trend Analysis'!D8 -> 0.45621956
A7: Net Profit Margin | D7: Total Debt | G7: Free Cash Flow
A8: ='Trend Analysis'!D9 -> 0.36146015 | D8: ='Trend Analysis'!D10 -> 43151 | G8: ='Trend Analysis'!D12 -> 71611
A44: Key Financial Insights
A46: Revenue Growth
A48: Revenue increased from $211.9B in FY2023 to $281.7B in FY2025, reflecting strong and consistent top-line growth.
A50: Profitability
A52: Operating profit margin improved from 41.77% to 45.62%, indicating stronger operating profitability over the three-year period.
A54: Net Profit
A56: Net income increased from $72.4B to $101.8B, while net profit margin improved from 34.15% to 36.15%.
A58: Debt Position
A60: Total debt declined from $47.7B in FY2023 to $43.2B in FY2025, while shareholders' equity increased significantly.
A62: Cash Flow
A64: Operating cash flow reached $136.2B in FY2025, while higher capital expenditure reduced free cash flow to $71.6B.

Sheet Trend Analysis
A1: Microsoft 3-Year Financial Trend Analysis
A2: Amounts in USD millions unless otherwise stated
A4: Financial Metric | B4: FY2023 | C4: FY2024 | D4: FY2025
A5: Revenue | B5: ='Income Statement'!B5 -> 211915 | C5: ='Income Statement'!C5 -> 245122 | D5: ='Income Statement'!D5 -> 281724
A6: Net Income | B6: ='Income Statement'!B14 -> 72361 | C6: ='Income Statement'!C14 -> 88136 | D6: ='Income Statement'!D14 -> 101832
A7: Gross Profit Margin | B7: ='Income Statement'!B16 -> 0.68920086 | C7: ='Income Statement'!C16 -> 0.69764444 | D7: ='Income Statement'!D16 -> 0.68823742
A8: Operating Profit Margin | B8: ='Income Statement'!B17 -> 0.41772881 | C8: ='Income Statement'!C17 -> 0.446443 | D8: ='Income Statement'!D17 -> 0.45621956
A9: Net Profit Margin | B9: ='Income Statement'!B18 -> 0.34146238 | C9: ='Income Statement'!C18 -> 0.35955973 | D9: ='Income Statement'!D18 -> 0.36146015
A10: Total Debt | B10: ='Balance Sheet'!B20 -> 47740 | C10: ='Balance Sheet'!C20 -> 51630 | D10: ='Balance Sheet'!D20 -> 43151
A11: Operating Cash Flow | B11: ='Cash Flow'!B6 -> 87582 | C11: ='Cash Flow'!C6 -> 118548 | D11: ='Cash Flow'!D6 -> 136162
A12: Free Cash Flow | B12: ='Cash Flow'!B12 -> 59475 | C12: ='Cash Flow'!C12 -> 74071 | D12: ='Cash Flow'!D12 -> 71611

Sheet Income Statement
A1: Microsoft Income Statement Analysis
A2: Amounts in USD millions
A4: Financial Metric | B4: FY2023 | C4: FY2024 | D4: FY2025 | E4: 2024 Growth | F4: 2025 Growth
A5: Revenue | B5: ='Raw Data'!B5 -> 211915 | C5: ='Raw Data'!C5 -> 245122 | D5: ='Raw Data'!D5 -> 281724 | E5: =(C5-B5)/B5 -> 0.15669962 | F5: =(D5-C5)/C5 -> 0.14932156
A6: Cost of Revenue | B6: ='Raw Data'!B6 -> 65863 | C6: ='Raw Data'!C6 -> 74114 | D6: ='Raw Data'!D6 -> 87831 | E6: =(C6-B6)/B6 -> 0.12527519 | F6: =(D6-C6)/C6 -> 0.18507974
A7: Gross Profit | B7: ='Raw Data'!B7 -> 146052 | C7: ='Raw Data'!C7 -> 171008 | D7: ='Raw Data'!D7 -> 193893 | E7: =(C7-B7)/B7 -> 0.17087065 | F7: =(D7-C7)/C7 -> 0.13382415
A8: Research & Development | B8: ='Raw Data'!B8 -> 27195 | C8: ='Raw Data'!C8 -> 29510 | D8: ='Raw Data'!D8 -> 32488 | E8: =(C8-B8)/B8 -> 0.085125942 | F8: =(D8-C8)/C8 -> 0.10091494
A9: Sales & Marketing | B9: ='Raw Data'!B9 -> 22759 | C9: ='Raw Data'!C9 -> 24456 | D9: ='Raw Data'!D9 -> 25654 | E9: =(C9-B9)/B9 -> 0.074563909 | F9: =(D9-C9)/C9 -> 0.048985934
A10: General & Administrative | B10: ='Raw Data'!B10 -> 7575 | C10: ='Raw Data'!C10 -> 7609 | D10: ='Raw Data'!D10 -> 7223 | E10: =(C10-B10)/B10 -> 0.0044884488 | F10: =(D10-C10)/C10 -> -0.050729399
A11: Operating Income | B11: ='Raw Data'!B11 -> 88523 | C11: ='Raw Data'!C11 -> 109433 | D11: ='Raw Data'!D11 -> 128528 | E11: =(C11-B11)/B11 -> 0.2362098 | F11: =(D11-C11)/C11 -> 0.17449033
A12: Income Before Tax | B12: ='Raw Data'!B12 -> 89311 | C12: ='Raw Data'!C12 -> 107787 | D12: ='Raw Data'!D12 -> 123627 | E12: =(C12-B12)/B12 -> 0.20687261 | F12: =(D12-C12)/C12 -> 0.1469565
A13: Income Tax | B13: ='Raw Data'!B13 -> 16950 | C13: ='Raw Data'!C13 -> 19651 | D13: ='Raw Data'!D13 -> 21795 | E13: =(C13-B13)/B13 -> 0.15935103 | F13: =(D13-C13)/C13 -> 0.10910386
A14: Net Income | B14: ='Raw Data'!B14 -> 72361 | C14: ='Raw Data'!C14 -> 88136 | D14: ='Raw Data'!D14 -> 101832 | E14: =(C14-B14)/B14 -> 0.21800417 | F14: =(D14-C14)/C14 -> 0.15539621
A16: Gross Profit Margin | B16: =B7/B5 -> 0.68920086 | C16: =C7/C5 -> 0.69764444 | D16: =D7/D5 -> 0.68823742
A17: Operating Profit Margin | B17: =B11/B5 -> 0.41772881 | C17: =C11/C5 -> 0.446443 | D17: =D11/D5 -> 0.45621956
A18: Net Profit Margin | B18: =B14/B5 -> 0.34146238 | C18: =C14/C5 -> 0.35955973 | D18: =D14/D5 -> 0.36146015

Sheet Balance Sheet
A1: Microsoft Balance Sheet Analysis
A2: Amounts in USD millions
A4: Financial Metric | B4: FY2023 | C4: FY2024 | D4: FY2025
A5: Cash & Cash Equivalents | B5: 34704 | C5: 18315 | D5: 30242
A6: Short-Term Investments | B6: 76558 | C6: 57228 | D6: 64323
A7: Accounts Receivable | B7: 48688 | C7: 56924 | D7: 69905
A8: Inventories | B8: 2500 | C8: 1246 | D8: 938
A9: Other Current Assets | B9: 21807 | C9: 26021 | D9: 25723
A10: Total Current Assets | B10: 184257 | C10: 159734 | D10: 191131
A11: Total Assets | B11: 411976 | C11: 512163 | D11: 619003
A12: Total Current Liabilities | B12: 104149 | C12: 125286 | D12: 141218
A13: Total Liabilities | B13: 205753 | C13: 243686 | D13: 275524
A14: Total Stockholders' Equity | B14: 206223 | C14: 268477 | D14: 343479
A15: Short-Term Debt | B15: 5750 | C15: 6693 | D15: 0
A16: Current Portion of Long-Term Debt | B16: 0 | C16: 2249 | D16: 2999
A17: Long-Term Debt | B17: 41990 | C17: 42688 | D17: 40152
A19: Current Ratio | B19: =B10/B12 -> 1.7691673 | C19: =C10/C12 -> 1.2749549 | D19: =D10/D12 -> 1.3534464
A20: Total Debt | B20: =SUM(B15:B17) -> 47740 | C20: =SUM(C15:C17) -> 51630 | D20: =SUM(D15:D17) -> 43151
A21: Debt-to-Equity Ratio | B21: =B20/B14 -> 0.23149697 | C21: =C20/C14 -> 0.19230698 | D21: =D20/D14 -> 0.12562922

Sheet Cash Flow
A1: Microsoft Cash Flow Analysis
A2: Amounts in USD millions
A4: Financial Metric | B4: FY2023 | C4: FY2024 | D4: FY2025
A5: Net Income | B5: 72361 | C5: 88136 | D5: 101832
A6: Net Cash from Operations | B6: 87582 | C6: 118548 | D6: 136162
A7: Additions to Property & Equipment | B7: -28107 | C7: -44477 | D7: -64551
A8: Net Cash Used in Investing | B8: -22680 | C8: -96970 | D8: -72599
A9: Net Cash Used in Financing | B9: -43935 | C9: -37757 | D9: -51699
A10: Net Change in Cash | B10: 20773 | C10: -16389 | D10: 11927
A11: Ending Cash & Cash Equivalents | B11: 34704 | C11: 18315 | D11: 30242
A12: Free Cash Flow | B12: =B6-ABS(B7) -> 59475 | C12: =C6-ABS(C7) -> 74071 | D12: =D6-ABS(D7) -> 71611
A14: Operating Cash Flow Margin | B14: =B6/'Income Statement'!B5 -> 0.41328835 | C14: =C6/'Income Statement'!C5 -> 0.48362856 | D14: =D6/'Income Statement'!D5 -> 0.48331701
A15: Free Cash Flow Margin | B15: =B12/'Income Statement'!B5 -> 0.28065498 | C15: =C12/'Income Statement'!C5 -> 0.30218014 | D15: =D12/'Income Statement'!D5 -> 0.2541885
A16: Cash Conversion Ratio | B16: =B6/B5 -> 1.2103481 | C16: =C6/C5 -> 1.3450576 | D16: =D6/D5 -> 1.3371239

Sheet DCF Valuation
A1: Microsoft DCF Valuation — Estimated Enterprise Value | G1: Growth Rate | H1: 0.08
A2: Base Year (FY2025) Free Cash Flow: $71,611 million | G2: Discount Rate (WACC) | H2: 0.1
G3: Terminal Growth Rate | H3: 0.025
A5: Year | B5: Projected FCF | C5: Discount Factor | D5: Present Value
A6: FY2026 | B6: ='Cash Flow'!D12*(1+'DCF Valuation'!H1) -> 77339.88 | C6: =1/(1+$H$2)^1 -> 0.90909091 | D6: =B6*C6 -> 70308.982
A7: FY2027 | B7: =B6*(1+$H$1) -> 83527.07 | C7: =1/(1+$H$2)^2 -> 0.82644628 | D7: =B7*C7 -> 69030.637
A8: FY2028 | B8: =B7*(1+$H$1) -> 90209.236 | C8: =1/(1+$H$2)^3 -> 0.7513148 | D8: =B8*C8 -> 67775.534
A9: FY2029 | B9: =B8*(1+$H$1) -> 97425.975 | C9: =1/(1+$H$2)^4 -> 0.68301346 | D9: =B9*C9 -> 66543.252
A10: FY2030 | B10: =B9*(1+$H$1) -> 105220.05 | C10: =1/(1+$H$2)^5 -> 0.62092132 | D10: =B10*C10 -> 65333.374
A12: Terminal Value | B12: =B10*(1+$H$3)/($H$2-$H$3) -> 1438007.4
A13: PV of Terminal Value | B13: =B12*C10 -> 892889.45
A15: Sum of PV of Projected FCF (FY26-30) | B15: =SUM(D6:D10) -> 338991.78
A16: Estimated Enterprise Value | B16: =B15+B13 -> 1231881.2
A18: Key Assumptions
A19: • Base year: FY2025 actual Free Cash Flow of $71,611 million (sourced from Cash Flow statement)
A20: • Growth rate: 8% annual FCF growth assumed for the 5-year explicit forecast period (FY2026-2030)
A21: • Discount rate (WACC): 10% assumed — a simplified estimate representative of large-cap technology companies, rather than a company-specific calculated WACC
A22: • Terminal growth rate: 2.5%, in line with long-term GDP/inflation expectations, used to estimate value beyond the 5-year forecast period (Gordon Growth Model)
A24: Result & Interpretation
A25: • Estimated Enterprise Value: ~$1.23 trillion, based on discounted 5-year FCF projections plus terminal value
A26: • This is notably lower than Microsoft's actual market capitalization (~$3.6-3.7 trillion as of August 2026), which is a common and expected outcome for simplified DCF models
A27: • Key reasons for the gap:
A28: 1. The 8% growth assumption is conservative relative to Microsoft's AI/cloud driven growth expectations;
A29: 2. The 10% discount rate is a generalized estimate rather than a precisely calculated WACC - a lower WACC would meaningfully increase the valuation;
A30: 3. DCF captures cash-generating ability from existing operations, while market value also prices in growth optionality (e.g., future AI products) that a standard 5-year model doesn't fully capture
A31: • This exercise demonstrates the DCF mechanics and sensitivity to assumptions, rather than serving as a precise real-world valuation — a useful reminder that model outputs are only as reliable as their inputs

Sheet Raw Data
A1: Microsoft Financial Statement Analysis
A2: Amounts in USD millions
A4: Financial Metric | B4: FY2023 | C4: FY2024 | D4: FY2025
A5: Revenue | B5: 211915 | C5: 245122 | D5: 281724
A6: Cost of Revenue | B6: 65863 | C6: 74114 | D6: 87831
A7: Gross Profit | B7: 146052 | C7: 171008 | D7: 193893
A8: Research & Development | B8: 27195 | C8: 29510 | D8: 32488
A9: Sales & Marketing | B9: 22759 | C9: 24456 | D9: 25654
A10: General & Administrative | B10: 7575 | C10: 7609 | D10: 7223
A11: Operating Income | B11: 88523 | C11: 109433 | D11: 128528
A12: Income Before Tax | B12: 89311 | C12: 107787 | D12: 123627
A13: Income Tax | B13: 16950 | C13: 19651 | D13: 21795
A14: Net Income | B14: 72361 | C14: 88136 | D14: 101832
