Workbook

Sheet Budget vs Actual
A1: Starbucks FY2024 Budget vs Actual Variance Analysis
A2: Fiscal Year Ended September 29, 2024 ($ in millions)
G3: FY2023 | I3: FY2024
A4: Line Item | B4: Budget (FY2024) | C4: Actual (FY2024) | D4: Variance ($) | E4: Variance (%) | F4: FY2023 Actual | G4: % of Revenue | I4: % of Revenue
A5: Company-operated stores revenue | B5: =F5*1.06 -> 31230.038 | C5: 29765.9 | D5: =C5-B5 -> -1464.138 | E5: =(C5-B5)/B5 -> -0.046882364 | F5: 29462.3
A6: Licensed stores revenue | B6: =F6*1.06 -> 4783.462 | C6: 4505.1 | D6: =C6-B6 -> -278.362 | E6: =(C6-B6)/B6 -> -0.058192581 | F6: 4512.7
A7: Other revenue | B7: =F7*1.06 -> 2120.636 | C7: 1905.2 | D7: =C7-B7 -> -215.436 | E7: =(C7-B7)/B7 -> -0.10159028 | F7: 2000.6
A8: Total net revenues | B8: =35975.6*1.06 -> 38134.136 | C8: 36176.2 | D8: =C8-B8 -> -1957.936 | E8: =(C8-B8)/B8 -> -0.051343395 | F8: 35975.6
A9: Product and distribution costs | B9: =$B$8*G9 -> 12093.646 | C9: 11180.6 | D9: =C9-B9 -> -913.046 | E9: =(C9-B9)/B9 -> -0.075497993 | F9: 11409.1 | G9: =F9/$F$8 -> 0.31713439 | I9: =Table2[[#This Row],[Actual (FY2024)]]/C8 -> 0.30905955
A10: Store operating expenses | B10: =$B$8*G10 -> 15603.518 | C10: 15286.5 | D10: =C10-B10 -> -317.018 | E10: =(C10-B10)/B10 -> -0.020317085 | F10: 14720.3 | G10: =F10/$F$8 -> 0.40917455 | I10: =Table2[[#This Row],[Actual (FY2024)]]/C8 -> 0.42255682
A11: Other operating expenses | B11: =$B$8*G11 -> 571.764 | C11: 565.6 | D11: =C11-B11 -> -6.164 | E11: =(C11-B11)/B11 -> -0.010780672 | F11: 539.4 | G11: =F11/$F$8 -> 0.014993496
A12: Depreciation and amortization | B12: =$B$8*G12 -> 1444.356 | C12: 1512.6 | D12: =C12-B12 -> 68.244 | E12: =(C12-B12)/B12 -> 0.047248739 | F12: 1362.6 | G12: =F12/$F$8 -> 0.037875671
A13: General and administrative expenses | B13: =$B$8*G13 -> 2587.778 | C13: 2523.3 | D13: =C13-B13 -> -64.478 | E13: =(C13-B13)/B13 -> -0.024916357 | F13: 2441.3 | G13: =F13/$F$8 -> 0.067859883 | I13: =Table2[[#This Row],[Actual (FY2024)]]/C8 -> 0.069750278
A14: Restructuring and impairments | B14: =$B$8*G14 -> 23.108 | C14: 0 | D14: =C14-B14 -> -23.108 | E14: =(C14-B14)/B14 -> -1 | F14: 21.8 | G14: =F14/$F$8 -> 0.00060596627
A15: Total operating expenses | B15: =$B$8*G15 -> 32324.17 | C15: 31068.6 | D15: =C15-B15 -> -1255.57 | E15: =(C15-B15)/B15 -> -0.03884307 | F15: 30494.5 | G15: =F15/$F$8 -> 0.84764396
A16: Income from equity investees | B16: =F16*1.06 -> 316.304 | C16: 301.2 | D16: =C16-B16 -> -15.104 | E16: =(C16-B16)/B16 -> -0.04775153 | F16: 298.4 | G16: =F16/$F$8 -> 0.0082945107
A17: Operating income | B17: =B8-B15+B16 -> 6126.27 | C17: 5408.8 | D17: =C17-B17 -> -717.47 | E17: =(C17-B17)/B17 -> -0.11711368 | F17: 5870.8 | G17: =F17/$F$8 -> 0.16318838
A18: Net earnings (Net income) | B18: =B8*G18 -> 4372.182 | C18: 3762.3 | D18: =C18-B18 -> -609.882 | E18: =(C18-B18)/B18 -> -0.13949145 | F18: 4124.7 | G18: =F18/$F$8 -> 0.11465271
A20: Key Assumptions
A21: • Revenue growth: 6% assumed across all revenue lines (Company-operated, Licensed, Other), based on recent historical growth trends
A22: • Cost line items: budgeted as % of FY2023 revenue (e.g., Product & distribution costs at 31.7%, Store operating expenses at 40.9%, G&A at 6.8%), assuming a similar cost structure would hold into FY2024
A23: • Net earnings: assumed at FY2023's net margin of 11.47% of revenue, for simplicity (a full model would build this up from operating income minus modeled interest and tax)
A25: Key Variance Drivers
A26: • Revenue missed budget by 5.1%, as actual growth (0.6% YoY) came in well below the 6% assumed — reflecting softer same-store sales and traffic than planned
A27: • Store operating expenses grew ~3.8% YoY in dollar terms and rose from 40.9% to 42.3% of revenue — a real cost overrun, even though it shows as "favorable" in dollar variance terms
A28: • Restructuring and impairment costs came in at zero vs. a small budgeted amount — a minor favorable variance with no material impact
A29: • Overall, both operating income (-11.7%) and net earnings (-14.0%) missed budget by a wider margin than revenue did — showing the shortfall was driven more by cost growth outpacing revenue than by the revenue miss alone

Sheet Rolling Forecast
A1: Starbucks FY2025 Rolling Forecast — Base, Upside & Downside Scenarios
A2: Fiscal Year 2025 Forecast ($ in millions)
A4: Line Item | B4: FY2024 Actual (Base) | C4: Base Case | D4: Upside Case | E4: Downside Case
A5: Total Net Revenues | B5: ='Budget vs Actual'!C8 -> 36176.2 | C5: =B5*(1+$B$17) -> 37261.486 | D5: =B5*(1+$B$18) -> 38346.772 | E5: =B5*(1+$B$19) -> 35814.438
A6: Product & Distribution Cost | B6: ='Budget vs Actual'!C9 -> 11180.6 | C6: =C5*D17 -> 11551.061 | D6: =D5*D18 -> 11504.032 | E6: =E5*D19 -> 11460.62
A7: Store Operating Expenses | B7: ='Budget vs Actual'!C10 -> 15286.5 | C7: =C5*C17 -> 15836.132 | D7: =D5*C18 -> 15722.177 | E7: =E5*C19 -> 15400.208
A8: General & Administration Expenses | B8: ='Budget vs Actual'!C13 -> 2523.3 | C8: =C5*E17 -> 2608.304 | D8: =D5*E18 -> 2492.5402 | E8: =E5*E19 -> 2686.0828
A9: Depreciation & amortization | B9: ='Budget vs Actual'!C12 -> 1512.6 | C9: =Table1[[#This Row],[FY2024 Actual (Base)]]*1.03 -> 1557.978 | D9: =Table1[[#This Row],[FY2024 Actual (Base)]]*1.02 -> 1542.852 | E9: =Table1[[#This Row],[FY2024 Actual (Base)]]*1.05 -> 1588.23
A10: Restructuring & Impairment | B10: 0 | C10: 0 | D10: 0 | E10: 50
A11: Total Operating Expenses | B11: =SUM(B6:B10) -> 30503 | C11: =SUM(C6:C10) -> 31553.474 | D11: =SUM(D6:D10) -> 31261.6 | E11: =SUM(E6:E10) -> 31185.141
A12: Operating income | B12: =B5-B11 -> 5673.2 | C12: =C5-C11 -> 5708.0118 | D12: =D5-D11 -> 7085.1717 | E12: =E5-E11 -> 4629.2967
C15: SOE | D15: P&D | E15: G&A
B16: Growth Rate | C16: % of Revenue | D16: % of Revenue | E16: % of Revenue
A17: Base Case | B17: 0.03 | C17: 0.425 | D17: 0.31 | E17: 0.07
A18: Upside Case | B18: 0.06 | C18: 0.41 | D18: 0.3 | E18: 0.065
A19: Downside Case | B19: -0.01 | C19: 0.43 | D19: 0.32 | E19: 0.075
A23: Key Assumptions
A24: • Revenue growth: Base Case assumes 3% growth (a recovery from FY2024's 0.6% actual growth, but below the originally budgeted 6%); Upside assumes 6% growth if sales trends improve; Downside assumes -1% if soft demand persists
A25: • Cost assumptions reflect the upward cost pressure identified in the FY2024 variance analysis — Store operating expenses are held at 41-43% of revenue (vs. 40.9% in FY2023), Product & distribution costs at 30-32%, and G&A at 6.5-7.5%, varying by scenario
A26: • Depreciation & amortization is grown modestly (2-5%) to reflect continued capital investment; Restructuring is assumed at zero except in the Downside case, where $50M is modeled for potential cost-cutting actions
A27: • Income from equity investees is excluded from this forecast for simplicity, given its immaterial size (~1% of revenue)
A29: Key Insight — Linking to Prior Variance Analysis
A30: • The FY2024 variance analysis showed that cost growth (particularly Store operating expenses) outpaced revenue growth, causing operating income to miss budget by a wider margin than revenue did
A31: • This forecast builds on that finding by assuming elevated cost ratios continue into FY2025 rather than reverting to FY2023 levels — even in the Base Case, costs remain above FY2023's historical average
A32: • As a result, even under the Upside Case (6% revenue growth), operating income margin improvement is modest, reflecting the structural cost pressure identified in the prior analysis

Sheet Business Case - Expansion
A1: Should Starbucks Open 50 New Stores? — ROI & Payback Analysis
A2: Business case evaluating a new store expansion initiative
A4: Number of New Stores | B4: 50
A5: Investment per Store | B5: 500000
A6: Year 1 Revenue per Store | B6: 1200000
A7: Store-Level Operating Margin | B7: 0.17
A9: Total Initial Investment | B9: =B4*B5 -> 25000000
A10: Total Year 1 Revenue | B10: =B4*B6 -> 60000000
A11: Total Year 1 Operating Profit | B11: =B7*B10 -> 10200000
A13: Payback Period (Year) | B13: =B9/B11 -> 2.4509804
A16: Annual Revenue Growth (as stores mature) | B16: 0.05
A17: Discount Rate (for NPV) | B17: 0.1

Sheet Business Case - Table
A1: 5-Year Projection & NPV Analysis
A2: Linked to Business Case - Expansion assumptions
A4: Store Level Operating Margin | B4: ='Business Case - Expansion'!B7 -> 0.17
A5: Annual Revenue Growth | B5: ='Business Case - Expansion'!B16 -> 0.05
A6: Discount Rate | B6: ='Business Case - Expansion'!B17 -> 0.1
A7: Total Initial Investment | B7: ='Business Case - Expansion'!B9 -> 25000000
A8: Year 1 Revenue | B8: ='Business Case - Expansion'!B10 -> 60000000
A10: Year | B10: Revenue | C10: Operating Profit | D10: Discount Factor | E10: Present Value of Profit
A11: Year 1 | B11: =B8 -> 60000000 | C11: =B11*B4 -> 10200000 | D11: =1/(1+$B$6)^1 -> 0.90909091 | E11: =C11*D11 -> 9272727.3
A12: Year 2 | B12: =B11*(1+$B$5) -> 63000000 | C12: =B12*$B$4 -> 10710000 | D12: =1/(1+$B$6)^2 -> 0.82644628 | E12: =C12*D12 -> 8851239.7
A13: Year 3 | B13: =B12*(1+$B$5) -> 66150000 | C13: =B13*$B$4 -> 11245500 | D13: =1/(1+$B$6)^3 -> 0.7513148 | E13: =C13*D13 -> 8448910.6
A14: Year 4 | B14: =B13*(1+$B$5) -> 69457500 | C14: =B14*$B$4 -> 11807775 | D14: =1/(1+$B$6)^4 -> 0.68301346 | E14: =C14*D14 -> 8064869.2
A15: Year 5 | B15: =B14*(1+$B$5) -> 72930375 | C15: =B15*$B$4 -> 12398164 | D15: =1/(1+$B$6)^5 -> 0.62092132 | E15: =C15*D15 -> 7698284.2
A17: NPV (5-Year) | B17: =SUM(E11:E15)-B7 -> 17336031
A20: Key Assumptions
A21: • Expansion scenario: 50 new company-operated stores
A22: • Initial investment ($500K/store) and Year 1 revenue ($1.2M/store) are based on third-party industry data for coffee retail store economics (Starbucks does not publicly disclose per-store financials)
A23: • Store-level operating margin (17%) is approximated from Starbucks' FY2023 company-wide operating margin (16.3%), used as a reasonable proxy since store-level margin data isn't public
A24: • Annual revenue growth (5%) reflects a general assumption for store maturation, not company-specific historical data
A25: • Discount rate (10%) — same rate used in the Microsoft DCF valuation, kept consistent across projects
A27: Results & Recommendation
A28: • Payback Period: 2.45 years — the initial $25 million investment is recovered from operating profit in under 2.5 years
A29: • 5-Year NPV: +$17.3 million — after discounting future profits back to present value and subtracting the initial investment, the expansion generates a net positive return of approximately $17.3 million
A30: • Recommendation: Proceed with the expansion. Both metrics point the same direction — a short payback period signals low risk (capital is recovered quickly), while a strongly positive NPV confirms the investment creates meaningful long-term value beyond simply recovering its cost
A31: • Limitation: This analysis uses industry-average unit economics rather than site-specific data (e.g., real estate costs, local market saturation, cannibalization of existing nearby stores), which would materially affect actual results for any specific expansion decision
